{
    "name": "009303 Z-Wave Plus Battery Wall Controller",
    "type": "Télécommande",
    "comlink": "3074-popp-controleur-mural-sans-fil-z-wave",
    "remark": "",
    "imglink": "popp.009303",
    "configuration": {
        "battery_type": "1x3V CR2032"
    },
    "versions": {
        "256": [
            "257"
        ]
    },
    "properties": {
        "CentralScene": {
            "multi": [
                1,
                2,
                3,
                4
            ],
            "replace": {
                "#centralscene#": "multiKey"
            }
        },
        "Battery": {}
    }
}